vec_inf/README.md
vec_inf/__init__.py
vec_inf/find_port.sh
vec_inf/cli/__init__.py
vec_inf/cli/_cli.py
vec_inf/cli/_helper.py
vec_inf/cli/_utils.py
vec_inf/cli/_vars.py
vec_inf/client/__init__.py
vec_inf/client/_client_vars.py
vec_inf/client/_exceptions.py
vec_inf/client/_helper.py
vec_inf/client/_slurm_script_generator.py
vec_inf/client/_slurm_templates.py
vec_inf/client/_slurm_vars.py
vec_inf/client/_utils.py
vec_inf/client/api.py
vec_inf/client/config.py
vec_inf/client/models.py
vec_inf/config/README.md
vec_inf/config/environment.yaml
vec_inf/config/models.yaml
vec_inf-0.8.0.dist-info/METADATA
vec_inf-0.8.0.dist-info/WHEEL
vec_inf-0.8.0.dist-info/entry_points.txt
vec_inf-0.8.0.dist-info/licenses/LICENSE
vec_inf-0.8.0.dist-info/RECORD
