Metadata-Version: 2.4
Name: vec-inf
Version: 0.8.0
Summary: Efficient LLM inference on Slurm clusters using vLLM.
Author-email: Marshall Wang <marshall.wang@vectorinstitute.ai>
License-Expression: MIT
License-File: LICENSE
Requires-Python: >=3.10
Requires-Dist: click>=8.1.0
Requires-Dist: pydantic>=2.10.6
Requires-Dist: pyyaml>=6.0.2
Requires-Dist: requests>=2.31.0
Requires-Dist: rich>=13.7.0
Provides-Extra: sglang
Requires-Dist: orjson>=3.11.0; extra == 'sglang'
Requires-Dist: sgl-kernel>=0.3.0; extra == 'sglang'
Requires-Dist: sglang>=0.5.5; extra == 'sglang'
Requires-Dist: torchao>=0.9.0; extra == 'sglang'
Provides-Extra: vllm
Requires-Dist: ray[default]>=2.51.0; extra == 'vllm'
Requires-Dist: vllm>=0.11.2; extra == 'vllm'
